html2dash/__init__.py
html2dash/html2dash.py
html2dash-0.2.4.dist-info/LICENSE
html2dash-0.2.4.dist-info/METADATA
html2dash-0.2.4.dist-info/WHEEL
html2dash-0.2.4.dist-info/top_level.txt
html2dash-0.2.4.dist-info/RECORD
