Metadata-Version: 2.1
Name: html2dash
Version: 0.2.4
Summary: Convert an HTML layout to a plotly dash layout
Author-email: Najeem Muhammed <najeem@gmail.com>
License: MIT License
Project-URL: Homepage, https://github.com/idling-mind/html2dash
Project-URL: Bug Tracker, https://github.com/idling-mind/html2dash/issues
Keywords: dash,plotly,html
Classifier: Programming Language :: Python :: 3
Classifier: License :: OSI Approved :: MIT License
Classifier: Operating System :: OS Independent
Requires-Python: >=3.7
License-File: LICENSE
Requires-Dist: dash
Requires-Dist: beautifulsoup4
Requires-Dist: lxml
Provides-Extra: test
Requires-Dist: pytest ; extra == 'test'
Requires-Dist: coverage ; extra == 'test'
